urbdict/__init__.py
urbdict/command_line.py
urbdict/main.py
urbdict-0.1.0.dist-info/LICENSE
urbdict-0.1.0.dist-info/METADATA
urbdict-0.1.0.dist-info/WHEEL
urbdict-0.1.0.dist-info/entry_points.txt
urbdict-0.1.0.dist-info/top_level.txt
urbdict-0.1.0.dist-info/RECORD
