Metadata-Version: 2.1
Name: urbdict
Version: 0.1.0
Summary: A library for urbandictionary.com
Home-page: https://github.com/RoastSea8/urbdict
Author: RoastSea8 (Aditya Tomar)
Author-email: aditya26042005@gmail.com
License: MIT
Keywords: urbandictionary,define,definitions,beautifulsoup,bs4,requests
Platform: UNKNOWN
Classifier: Development Status :: 5 - Production/Stable
Classifier: Topic :: Software Development :: Libraries :: Python Modules
Classifier: License :: OSI Approved :: MIT License
Classifier: Programming Language :: Python :: 3
Classifier: Programming Language :: Python :: 3.6
Classifier: Programming Language :: Python :: 3.7
Classifier: Programming Language :: Python :: 3.8
Classifier: Programming Language :: Python :: 3.9
Classifier: Programming Language :: Python :: 3.10
Classifier: Operating System :: MacOS :: MacOS X
Classifier: Operating System :: Microsoft :: Windows
Requires-Python: >=3.6
License-File: LICENSE
Requires-Dist: requests
Requires-Dist: bs4
Requires-Dist: lxml
